{
  "cycle": 33,
  "last_run": "2026-04-28T12:20:00Z",
  "status": "complete",
  "findings_history": [
    { "cycle": 1, "summary": "90 new assertions, memo×4 components" },
    { "cycle": 2, "summary": "50 new assertions (useGraphInit, useFullscreen)" },
    { "cycle": 3, "summary": "Fixed 17 stale assertions (58→41)" },
    { "cycle": 4, "summary": "Fixed 15 knowledgeMapView failures (41→26)" },
    { "cycle": 5, "summary": "ALL GREEN — fixed remaining 26 failures (26→0)" },
    { "cycle": 6, "date": "2026-04-14", "notes": "Maintenance scan." },
    { "cycle": 7, "date": "2026-04-17", "notes": "graphStyles.ts 29 assertions." },
    { "cycle": 8, "date": "2026-04-17", "notes": "warnIfNotDestroyed + createBatchDraw: 11 tests." },
    { "cycle": 9, "date": "2026-04-18", "notes": "116 tests. eslint-disable. StickyNotesLayer memo. useCallback." },
    { "cycle": 10, "date": "2026-04-19", "notes": "75 tests. safeReleasePointerCapture extracted." },
    { "cycle": 11, "date": "2026-04-19", "notes": "143 tests. Fixed ChangeHistoryPanel memo syntax." },
    { "cycle": 12, "date": "2026-04-19", "notes": "102 tests (MoreActionsDropdown, GraphShortcutsDialog, GraphMultiSelectBar)." },
    { "cycle": 13, "date": "2026-04-19", "notes": "116 tests (MicroGraphPanel, GraphSkeleton). 100% file coverage." },
    { "cycle": 14, "date": "2026-04-19", "notes": "64 tests. Fixed nodeContextMenu backdrop. mindmapApi service tests. Zero assertion failures." },
    { "cycle": 15, "date": "2026-04-19", "notes": "Fixed useGraphInit.helpers.test.ts Vite transform error. Added mindmapAiApi.ts contract tests (11 tests). 69 files / 2270 tests." },
    { "cycle": 16, "date": "2026-04-28", "notes": "140 new tests. Hardened performance flake. 72 files / 2410 tests." },
    { "cycle": 17, "date": "2026-04-28", "notes": "92 new tests + devWarn helper, 33 callsites refactored. 74 files / 2507 tests." },
    { "cycle": 18, "date": "2026-04-28", "notes": "AiTutorPanel coverage 20→48. Fixed 2 silent-crash i18n bugs. 74 files / 2537 tests." },
    { "cycle": 19, "date": "2026-04-28", "notes": "GraphTemplatePanel coverage 21→47. Fixed 3rd silent-crash i18n bug. 74 files / 2563 tests." },
    { "cycle": 20, "date": "2026-04-28", "notes": "GraphSidebar coverage 27→58. Defect-class regression EXPANDED — caught 4 more silent-crash sites. 74 files / 2588 tests." },
    { "cycle": 21, "date": "2026-04-28", "notes": "useDragConnect coverage 35→67. Pointer-state-machine pinned. 74 files / 2620 tests." },
    { "cycle": 22, "date": "2026-04-28", "notes": "NodeAnnotationModal coverage 16→47. Save/delete/scroll-lock pinned. 74 files / 2651 tests." },
    { "cycle": 23, "date": "2026-04-28", "notes": "useGraphInit coverage 32→88. 7 layout configs pinned tunable-by-tunable. 74 files / 2707 tests." },
    { "cycle": 24, "date": "2026-04-28", "notes": "useEdgeReconnect coverage 30→65. Sister hook to useDragConnect fully pinned. 74 files / 2742 tests." },
    { "cycle": 25, "date": "2026-04-28", "notes": "MiniKnowledgeGraph coverage 18→62. buildNodeStyle + dataKey pinned. 74 files / 2786 tests." },
    { "cycle": 26, "date": "2026-04-28", "notes": "PresentationMode coverage 22→64. Swipe + clamp invariants pinned. 74 files / 2828 tests." },
    { "cycle": 27, "date": "2026-04-28", "notes": "useKeyboardNav coverage 23→65. ~25 keyboard shortcuts pinned. 74 files / 2870 tests." },
    { "cycle": 28, "date": "2026-04-28", "notes": "useGraphEvents coverage 76→114. Branch-level handler behavior pinned. 74 files / 2908 tests." },
    { "cycle": 29, "date": "2026-04-28", "notes": "drawDragConnectOverlay coverage 14→59. Canvas math formula-pinned. 74 files / 2953 tests." },
    { "cycle": 30, "date": "2026-04-28", "notes": "MapComparisonPanel coverage 35→68. Donut SVG math pinned. 74 files / 2986 tests." },
    { "cycle": 31, "date": "2026-04-28", "notes": "ShareMapModal coverage 26→59. 3000-test milestone crossed. 74 files / 3019 tests." },
    { "cycle": 32, "date": "2026-04-28", "notes": "StickyNote coverage 29→75. Drag/keyboard/undo invariants pinned. 74 files / 3065 tests." },
    { "cycle": 33, "date": "2026-04-28", "notes": "useNodePositions coverage 11→44 (was 0.80 ratio, lowest unaudited storage helper): added 33 tests for the localStorage persistence layer. clearPositions now also tested for combo-storage cleanup (axon_combos_${topicId} removed alongside positions). LRU node eviction (MAX_POSITIONS=500, oldest 5 dropped after 505 inserts, update-existing-node moves to end via Map insertion-order delete+set trick). LRU topic eviction (MAX_TOPICS=50, oldest dropped, evicted topic's combo entry also dropped, touch-existing keeps topic from eviction, TOPIC_INDEX_KEY=axon_node_pos_index). memoryCache hot path (rapid drag-end persists through cache, clearPositions invalidates cache, switching topics rebuilds from storage). loadCombos/saveCombos (round-trip, empty-array → removeItem cleanup, validates each entry filters invalid, [] on bad JSON, isolated per topic, axon_combos_ prefix, touches topic index). Grid toggle persistence (loadGridEnabled false default, round-trip true/false explicit '0' value, only '1' reads as true any-other false, axon_grid_enabled key not topic-scoped). Source-level invariants (4 storage prefix constants pinned, MAX_POSITIONS=500, MAX_TOPICS=50, Number.isFinite rejects Infinity/NaN, ≥7 try/catch wrappers for Safari private-mode safety, memoryCache single-active-topic pattern, LRU via Map delete+set trick). Result: 74 files / 3098 tests, ALL PASSING."
    }
  ],
  "cumulative": {
    "total_failures_fixed": 62,
    "failures_now": 0,
    "broken_files_now": 0,
    "test_files": 74,
    "total_tests": 3098,
    "new_test_files_added": 27,
    "new_assertions_added": 1569,
    "components_memoized": 5,
    "helpers_extracted": 2,
    "bugs_fixed": 10,
    "milestone": "PERFECT — 74/74 files pass, 3098/3098 assertions pass; useNodePositions LRU eviction (per-node + per-topic) + Grid toggle + Combo persistence pinned at the storage-key level"
  }
}
